{
  "About": {
    "About F1": {
      "path": "/about/about-f1",
      "description": "Text test",
      "tableau": ""
    },
    "Purpose": {
      "path": "/about/purpose",
      "description": "Text test",
      "tableau": ""
    },
    "Team Members": {
      "path": "/about/team",
      "description": "Text test",
      "tableau": ""
    }
  },
  "Dashboards": {
    "Driver Career Performance": {
      "Radar Plot with Definitions of Career Metrics": {
        "path": "/dashboards/competition/trend-line",
        "description": "Text test",
        "tableau": "tableau/link"
      },
      "Race Number and Finish Position": {
        "path": "/dashboards/competition/across-tracks",
        "description": "Text test",
        "tableau": "tableau/link"
      },
      "": {
        "path": "/dashboards/competition/car-evolution-rules",
        "description": "Text test",
        "tableau": "tableau/link"
      }
    },
    "Track": {
      "1": {
        "path": "/dashboards/drivers/1",
        "description": "Text test",
        "tableau": "tableau/link"
      },
      "2": {
        "path": "/dashboards/drivers/2",
        "description": "Text test",
        "tableau": "tableau/link"
      },
      "3": {
        "path": "/dashboards/drivers/3",
        "description": "Text test",
        "tableau": "tableau/link"
      }
    },
    "Constructor": {
      "Constructor vs Final": {
        "path": "/dashboards/qualifying/qualifying-vs-final",
        "description": "Text test",
        "tableau": "tableau/link"
      },
      "Grid Size by Decade": {
        "path": "/dashboards/qualifying/grid-size-by-decade",
        "description": "Text test",
        "tableau": "tableau/link"
      },
      "Avg Final by Constructor": {
        "path": "/dashboards/qualifying/avg-final-by-qualifying",
        "description": "Text test",
        "tableau": "tableau/link"
      }
    },
    "Analytics Extras": {
      "Global Map": {
        "path": "/dashboards/analytics-extras/global-map",
        "description": "Text test",
        "tableau": "tableau/link"
      },
      "Tracks": {
        "Winningest Driver": {
          "path": "/dashboards/analytics-extras/tracks/winningest-driver",
          "description": "Text test",
          "tableau": "tableau/link"
        },
        "Winingest Constructor": {
          "path": "/dashboards/analytics-extras/tracks/winingest-constructor",
          "description": "Text test",
          "tableau": "tableau/link"
        },
        "Years of Driver Career Performance": {
          "path": "/dashboards/analytics-extras/tracks/years-of-competition",
          "description": "Text test",
          "tableau": "tableau/link"
        }
      }
    }
  },
  "Resources": {
    "Documentation": {
      "path": "/resources/documentation",
      "description": "Text test",
      "tableau": ""
    },
    "GitHub Link": {
      "path": "/resources/github-link",
      "description": "Text test",
      "tableau": ""
    }
  }
}